{
  "slug": "makroekonomika-eurozony",
  "description": "Eurozone macro: M aggregates, key rates, EURIBOR, yields, inflation, velocity",
  "generatedAt": "2026-05-01T06:40:13.571Z",
  "data": {
    "aggregates": {
      "times": [
        "1980-01",
        "1980-02",
        "1980-03",
        "1980-04",
        "1980-05",
        "1980-06",
        "1980-07",
        "1980-08",
        "1980-09",
        "1980-10",
        "1980-11",
        "1980-12",
        "1981-01",
        "1981-02",
        "1981-03",
        "1981-04",
        "1981-05",
        "1981-06",
        "1981-07",
        "1981-08",
        "1981-09",
        "1981-10",
        "1981-11",
        "1981-12",
        "1982-01",
        "1982-02",
        "1982-03",
        "1982-04",
        "1982-05",
        "1982-06",
        "1982-07",
        "1982-08",
        "1982-09",
        "1982-10",
        "1982-11",
        "1982-12",
        "1983-01",
        "1983-02",
        "1983-03",
        "1983-04",
        "1983-05",
        "1983-06",
        "1983-07",
        "1983-08",
        "1983-09",
        "1983-10",
        "1983-11",
        "1983-12",
        "1984-01",
        "1984-02",
        "1984-03",
        "1984-04",
        "1984-05",
        "1984-06",
        "1984-07",
        "1984-08",
        "1984-09",
        "1984-10",
        "1984-11",
        "1984-12",
        "1985-01",
        "1985-02",
        "1985-03",
        "1985-04",
        "1985-05",
        "1985-06",
        "1985-07",
        "1985-08",
        "1985-09",
        "1985-10",
        "1985-11",
        "1985-12",
        "1986-01",
        "1986-02",
        "1986-03",
        "1986-04",
        "1986-05",
        "1986-06",
        "1986-07",
        "1986-08",
        "1986-09",
        "1986-10",
        "1986-11",
        "1986-12",
        "1987-01",
        "1987-02",
        "1987-03",
        "1987-04",
        "1987-05",
        "1987-06",
        "1987-07",
        "1987-08",
        "1987-09",
        "1987-10",
        "1987-11",
        "1987-12",
        "1988-01",
        "1988-02",
        "1988-03",
        "1988-04",
        "1988-05",
        "1988-06",
        "1988-07",
        "1988-08",
        "1988-09",
        "1988-10",
        "1988-11",
        "1988-12",
        "1989-01",
        "1989-02",
        "1989-03",
        "1989-04",
        "1989-05",
        "1989-06",
        "1989-07",
        "1989-08",
        "1989-09",
        "1989-10",
        "1989-11",
        "1989-12",
        "1990-01",
        "1990-02",
        "1990-03",
        "1990-04",
        "1990-05",
        "1990-06",
        "1990-07",
        "1990-08",
        "1990-09",
        "1990-10",
        "1990-11",
        "1990-12",
        "1991-01",
        "1991-02",
        "1991-03",
        "1991-04",
        "1991-05",
        "1991-06",
        "1991-07",
        "1991-08",
        "1991-09",
        "1991-10",
        "1991-11",
        "1991-12",
        "1992-01",
        "1992-02",
        "1992-03",
        "1992-04",
        "1992-05",
        "1992-06",
        "1992-07",
        "1992-08",
        "1992-09",
        "1992-10",
        "1992-11",
        "1992-12",
        "1993-01",
        "1993-02",
        "1993-03",
        "1993-04",
        "1993-05",
        "1993-06",
        "1993-07",
        "1993-08",
        "1993-09",
        "1993-10",
        "1993-11",
        "1993-12",
        "1994-01",
        "1994-02",
        "1994-03",
        "1994-04",
        "1994-05",
        "1994-06",
        "1994-07",
        "1994-08",
        "1994-09",
        "1994-10",
        "1994-11",
        "1994-12",
        "1995-01",
        "1995-02",
        "1995-03",
        "1995-04",
        "1995-05",
        "1995-06",
        "1995-07",
        "1995-08",
        "1995-09",
        "1995-10",
        "1995-11",
        "1995-12",
        "1996-01",
        "1996-02",
        "1996-03",
        "1996-04",
        "1996-05",
        "1996-06",
        "1996-07",
        "1996-08",
        "1996-09",
        "1996-10",
        "1996-11",
        "1996-12",
        "1997-01",
        "1997-02",
        "1997-03",
        "1997-04",
        "1997-05",
        "1997-06",
        "1997-07",
        "1997-08",
        "1997-09",
        "1997-10",
        "1997-11",
        "1997-12",
        "1998-01",
        "1998-02",
        "1998-03",
        "1998-04",
        "1998-05",
        "1998-06",
        "1998-07",
        "1998-08",
        "1998-09",
        "1998-10",
        "1998-11",
        "1998-12",
        "1999-01",
        "1999-02",
        "1999-03",
        "1999-04",
        "1999-05",
        "1999-06",
        "1999-07",
        "1999-08",
        "1999-09",
        "1999-10",
        "1999-11",
        "1999-12",
        "2000-01",
        "2000-02",
        "2000-03",
        "2000-04",
        "2000-05",
        "2000-06",
        "2000-07",
        "2000-08",
        "2000-09",
        "2000-10",
        "2000-11",
        "2000-12",
        "2001-01",
        "2001-02",
        "2001-03",
        "2001-04",
        "2001-05",
        "2001-06",
        "2001-07",
        "2001-08",
        "2001-09",
        "2001-10",
        "2001-11",
        "2001-12",
        "2002-01",
        "2002-02",
        "2002-03",
        "2002-04",
        "2002-05",
        "2002-06",
        "2002-07",
        "2002-08",
        "2002-09",
        "2002-10",
        "2002-11",
        "2002-12",
        "2003-01",
        "2003-02",
        "2003-03",
        "2003-04",
        "2003-05",
        "2003-06",
        "2003-07",
        "2003-08",
        "2003-09",
        "2003-10",
        "2003-11",
        "2003-12",
        "2004-01",
        "2004-02",
        "2004-03",
        "2004-04",
        "2004-05",
        "2004-06",
        "2004-07",
        "2004-08",
        "2004-09",
        "2004-10",
        "2004-11",
        "2004-12",
        "2005-01",
        "2005-02",
        "2005-03",
        "2005-04",
        "2005-05",
        "2005-06",
        "2005-07",
        "2005-08",
        "2005-09",
        "2005-10",
        "2005-11",
        "2005-12",
        "2006-01",
        "2006-02",
        "2006-03",
        "2006-04",
        "2006-05",
        "2006-06",
        "2006-07",
        "2006-08",
        "2006-09",
        "2006-10",
        "2006-11",
        "2006-12",
        "2007-01",
        "2007-02",
        "2007-03",
        "2007-04",
        "2007-05",
        "2007-06",
        "2007-07",
        "2007-08",
        "2007-09",
        "2007-10",
        "2007-11",
        "2007-12",
        "2008-01",
        "2008-02",
        "2008-03",
        "2008-04",
        "2008-05",
        "2008-06",
        "2008-07",
        "2008-08",
        "2008-09",
        "2008-10",
        "2008-11",
        "2008-12",
        "2009-01",
        "2009-02",
        "2009-03",
        "2009-04",
        "2009-05",
        "2009-06",
        "2009-07",
        "2009-08",
        "2009-09",
        "2009-10",
        "2009-11",
        "2009-12",
        "2010-01",
        "2010-02",
        "2010-03",
        "2010-04",
        "2010-05",
        "2010-06",
        "2010-07",
        "2010-08",
        "2010-09",
        "2010-10",
        "2010-11",
        "2010-12",
        "2011-01",
        "2011-02",
        "2011-03",
        "2011-04",
        "2011-05",
        "2011-06",
        "2011-07",
        "2011-08",
        "2011-09",
        "2011-10",
        "2011-11",
        "2011-12",
        "2012-01",
        "2012-02",
        "2012-03",
        "2012-04",
        "2012-05",
        "2012-06",
        "2012-07",
        "2012-08",
        "2012-09",
        "2012-10",
        "2012-11",
        "2012-12",
        "2013-01",
        "2013-02",
        "2013-03",
        "2013-04",
        "2013-05",
        "2013-06",
        "2013-07",
        "2013-08",
        "2013-09",
        "2013-10",
        "2013-11",
        "2013-12",
        "2014-01",
        "2014-02",
        "2014-03",
        "2014-04",
        "2014-05",
        "2014-06",
        "2014-07",
        "2014-08",
        "2014-09",
        "2014-10",
        "2014-11",
        "2014-12",
        "2015-01",
        "2015-02",
        "2015-03",
        "2015-04",
        "2015-05",
        "2015-06",
        "2015-07",
        "2015-08",
        "2015-09",
        "2015-10",
        "2015-11",
        "2015-12",
        "2016-01",
        "2016-02",
        "2016-03",
        "2016-04",
        "2016-05",
        "2016-06",
        "2016-07",
        "2016-08",
        "2016-09",
        "2016-10",
        "2016-11",
        "2016-12",
        "2017-01",
        "2017-02",
        "2017-03",
        "2017-04",
        "2017-05",
        "2017-06",
        "2017-07",
        "2017-08",
        "2017-09",
        "2017-10",
        "2017-11",
        "2017-12",
        "2018-01",
        "2018-02",
        "2018-03",
        "2018-04",
        "2018-05",
        "2018-06",
        "2018-07",
        "2018-08",
        "2018-09",
        "2018-10",
        "2018-11",
        "2018-12",
        "2019-01",
        "2019-02",
        "2019-03",
        "2019-04",
        "2019-05",
        "2019-06",
        "2019-07",
        "2019-08",
        "2019-09",
        "2019-10",
        "2019-11",
        "2019-12",
        "2020-01",
        "2020-02",
        "2020-03",
        "2020-04",
        "2020-05",
        "2020-06",
        "2020-07",
        "2020-08",
        "2020-09",
        "2020-10",
        "2020-11",
        "2020-12",
        "2021-01",
        "2021-02",
        "2021-03",
        "2021-04",
        "2021-05",
        "2021-06",
        "2021-07",
        "2021-08",
        "2021-09",
        "2021-10",
        "2021-11",
        "2021-12",
        "2022-01",
        "2022-02",
        "2022-03",
        "2022-04",
        "2022-05",
        "2022-06",
        "2022-07",
        "2022-08",
        "2022-09",
        "2022-10",
        "2022-11",
        "2022-12",
        "2023-01",
        "2023-02",
        "2023-03",
        "2023-04",
        "2023-05",
        "2023-06",
        "2023-07",
        "2023-08",
        "2023-09",
        "2023-10",
        "2023-11",
        "2023-12",
        "2024-01",
        "2024-02",
        "2024-03",
        "2024-04",
        "2024-05",
        "2024-06",
        "2024-07",
        "2024-08",
        "2024-09",
        "2024-10",
        "2024-11",
        "2024-12",
        "2025-01",
        "2025-02",
        "2025-03",
        "2025-04",
        "2025-05",
        "2025-06",
        "2025-07",
        "2025-08",
        "2025-09",
        "2025-10",
        "2025-11",
        "2025-12",
        "2026-01",
        "2026-02",
        "2026-03"
      ],
      "m1": [
        444330,
        447116,
        451370,
        453226,
        455917,
        458753,
        464938,
        465216,
        466718,
        473228,
        476657,
        473379,
        476622,
        480316,
        481349,
        482746,
        486588,
        487093,
        488660,
        489042,
        493362,
        494975,
        497550,
        499258,
        504513,
        507652,
        512323,
        517834,
        519493,
        525037,
        527685,
        534112,
        537908,
        540880,
        548081,
        551435,
        556058,
        561066,
        564440,
        569885,
        574912,
        581509,
        586440,
        589345,
        590795,
        593003,
        597800,
        603201,
        605312,
        607750,
        610604,
        613037,
        618405,
        620180,
        623188,
        630220,
        633449,
        636282,
        641335,
        649438,
        655896,
        660173,
        662471,
        662313,
        664412,
        667103,
        673104,
        676373,
        681849,
        688046,
        691122,
        698795,
        702125,
        709952,
        724787,
        722982,
        730348,
        729246,
        737933,
        743114,
        748489,
        756418,
        758059,
        760344,
        767204,
        770640,
        777454,
        785292,
        788094,
        796118,
        800728,
        803222,
        809350,
        815589,
        816949,
        815428,
        824174,
        827054,
        832408,
        843094,
        848492,
        854395,
        863859,
        868224,
        869720,
        877198,
        881397,
        882693,
        888361,
        893464,
        908243,
        901575,
        907746,
        920566,
        926896,
        933145,
        935497,
        941093,
        947348,
        956837,
        965584,
        965756,
        965508,
        966414,
        972359,
        1006819,
        1014117,
        1022099,
        1028301,
        1027958,
        1033314,
        1058884,
        1056331,
        1065570,
        1059848,
        1064370,
        1070969,
        1073039,
        1080404,
        1083755,
        1081506,
        1081901,
        1091345,
        1099507,
        1093150,
        1092910,
        1100845,
        1108333,
        1114672,
        1109260,
        1113660,
        1115857,
        1128821,
        1132818,
        1145342,
        1144131,
        1139862,
        1141771,
        1152504,
        1155244,
        1159512,
        1166557,
        1170031,
        1175388,
        1183230,
        1198003,
        1213444,
        1221682,
        1234252,
        1241994,
        1254183,
        1257216,
        1251928,
        1260722,
        1262275,
        1268603,
        1271745,
        1278103,
        1273612,
        1273837,
        1270347,
        1279599,
        1279786,
        1280661,
        1288668,
        1291901,
        1295406,
        1300280,
        1313848,
        1312908,
        1320636,
        1349298,
        1342826,
        1342788,
        1347622,
        1360812,
        1367743,
        1370698,
        1379242,
        1391358,
        1403713,
        1413817,
        1431291,
        1458860,
        1455766,
        1462263,
        1462135,
        1462884,
        1481529,
        1497996,
        1511944,
        1519774,
        1529659,
        1553269,
        1552044,
        1566011,
        1574257,
        1586035,
        1606018,
        1619997,
        1633711,
        1657166,
        1652445,
        1659698,
        1668328,
        1683846,
        1702749,
        1726398,
        1807005,
        1785973,
        1806407,
        1823152,
        1836913,
        1858495,
        1882493,
        1879218,
        1886642,
        1900478,
        1912382,
        1925201,
        1986266,
        1987628,
        2003675,
        2022293,
        2005841,
        2001262,
        2011982,
        2022187,
        2015210,
        2022687,
        2019092,
        2025182,
        2094231,
        2104954,
        2106179,
        2124789,
        2142955,
        2158667,
        2157872,
        2173000,
        2190698,
        2202764,
        2220198,
        2221922,
        2247196,
        2248416,
        2238965,
        2273547,
        2293570,
        2304238,
        2323079,
        2340395,
        2369110,
        2380902,
        2417288,
        2442884,
        2454715,
        2481185,
        2499997,
        2531994,
        2549757,
        2558373,
        2576935,
        2607442,
        2623849,
        2655345,
        2663643,
        2681722,
        2704804,
        2722810,
        2760683,
        2776949,
        2774765,
        2796512,
        2820299,
        2834917,
        2868123,
        2888055,
        2913177,
        2905953,
        2963795,
        2990384,
        3006328,
        3024122,
        3054725,
        3256960,
        3302577,
        3323473,
        3343523,
        3370621,
        3390768,
        3422279,
        3445371,
        3470031,
        3489442,
        3523343,
        3553540,
        3560905,
        3554322,
        3565013,
        3590868,
        3589937,
        3617914,
        3696019,
        3696560,
        3718712,
        3746750,
        3744814,
        3773413,
        3794192,
        3821040,
        3810958,
        3831681,
        3829110,
        3854352,
        3839555,
        3852397,
        3845184,
        3859561,
        3840284,
        3857591,
        3857729,
        3828594,
        3822371,
        3884458,
        3977681,
        3967905,
        3992578,
        4091136,
        4132097,
        4147215,
        4190537,
        4207878,
        4258226,
        4314634,
        4346194,
        4400713,
        4448680,
        4467737,
        4499550,
        4545385,
        4568331,
        4580958,
        4632696,
        4649309,
        4674690,
        4680518,
        4693166,
        4676240,
        4678750,
        4687979,
        4710694,
        4715716,
        4718429,
        4727336,
        4712016,
        4710610,
        4728150,
        4730745,
        4764855,
        4774497,
        4779936,
        4790210,
        4803786,
        4821347,
        4824871,
        4856040,
        4831364,
        4881060,
        4909295,
        4971911,
        5004569,
        5025079,
        5072266,
        5096612,
        5102595,
        5105555,
        5144982,
        5173010,
        5215171,
        5241782,
        5240787,
        5272637,
        5314438,
        5345103,
        5380840,
        5402217,
        5386119,
        5416893,
        5451336,
        5475017,
        5479764,
        5516258,
        5548049,
        5580718,
        5626751,
        5683788,
        5723293,
        5788176,
        5941966,
        6037612,
        6091007,
        6151855,
        6206168,
        6271825,
        6325590,
        6392616,
        6424845,
        6459866,
        6527378,
        6583484,
        6612393,
        6670355,
        6733011,
        6757516,
        6804786,
        6849266,
        6871798,
        6928484,
        6970524,
        7005097,
        7059544,
        7137436,
        7158597,
        7208244,
        7263871,
        7344648,
        7394158,
        7423638,
        7488142,
        7522548,
        7579897,
        7621867,
        7666219,
        7713565,
        7749170,
        7816816,
        7838336,
        7860032,
        7917301,
        7994225,
        8039727,
        8059263,
        8090032,
        8147600,
        8198188,
        8247027,
        8290550,
        8323715,
        8375749,
        8459043,
        8514430,
        8574059,
        8613766,
        8684066,
        8768593,
        8821267,
        8891862,
        8933290,
        8951049,
        8995503,
        9059015,
        9360114,
        9527628,
        9638421,
        9736833,
        9798649,
        9870472,
        9944815,
        10052369,
        10164449,
        10273062,
        10374220,
        10465077,
        10563963,
        10621142,
        10700843,
        10799517,
        10898215,
        11003766,
        11086933,
        11145446,
        11190661,
        11299553,
        11388865,
        11474822,
        11532853,
        11556470,
        11604215,
        11641614,
        11689990,
        11781516,
        11694702,
        11567647,
        11439544,
        11304904,
        11264981,
        11139275,
        11008819,
        10886479,
        10807611,
        10704881,
        10628838,
        10551973,
        10514209,
        10417745,
        10362276,
        10354466,
        10279345,
        10255633,
        10245525,
        10246046,
        10248211,
        10310164,
        10287484,
        10347634,
        10402301,
        10450129,
        10536584,
        10603156,
        10594616,
        10647792,
        10682624,
        10736082,
        10771551,
        10806796,
        10812716,
        10840616,
        10896148,
        10994528,
        11059015,
        11092498,
        11222811,
        11234619,
        11279794
      ],
      "m2": [
        1070496,
        1078232,
        1088333,
        1093263,
        1100958,
        1109205,
        1120452,
        1127098,
        1133419,
        1145159,
        1160031,
        1165452,
        1175008,
        1186668,
        1194414,
        1204188,
        1215847,
        1223076,
        1230470,
        1234000,
        1246150,
        1253958,
        1264026,
        1273805,
        1287848,
        1299092,
        1313351,
        1326733,
        1334764,
        1347524,
        1358609,
        1372472,
        1382740,
        1389853,
        1401761,
        1414556,
        1425088,
        1435898,
        1443423,
        1453878,
        1464343,
        1474969,
        1486582,
        1498206,
        1503408,
        1513481,
        1526253,
        1537092,
        1543563,
        1549774,
        1559014,
        1568820,
        1583749,
        1591965,
        1603857,
        1617813,
        1631220,
        1638411,
        1649653,
        1661882,
        1676415,
        1691806,
        1700138,
        1709983,
        1715317,
        1722006,
        1731220,
        1738364,
        1746936,
        1755357,
        1760581,
        1784034,
        1792537,
        1800828,
        1818276,
        1815354,
        1824547,
        1832456,
        1847233,
        1858580,
        1872837,
        1889296,
        1896941,
        1903734,
        1918425,
        1927091,
        1940390,
        1952955,
        1962800,
        1975973,
        1985755,
        1992865,
        2002177,
        2016290,
        2024128,
        2027444,
        2037581,
        2046281,
        2057427,
        2076081,
        2090533,
        2100900,
        2116901,
        2131825,
        2139817,
        2154925,
        2167024,
        2173774,
        2185797,
        2197853,
        2222161,
        2224430,
        2240671,
        2263203,
        2280165,
        2292824,
        2303555,
        2312607,
        2326287,
        2343345,
        2360748,
        2368976,
        2371264,
        2378067,
        2386578,
        2494707,
        2506891,
        2521801,
        2539282,
        2548320,
        2560619,
        2573883,
        2583655,
        2601663,
        2601696,
        2615487,
        2630099,
        2639742,
        2650528,
        2665240,
        2672023,
        2683318,
        2704447,
        2722085,
        2720803,
        2729621,
        2747609,
        2764811,
        2778249,
        2784130,
        2792853,
        2803439,
        2836589,
        2839113,
        2860628,
        2853356,
        2861813,
        2876975,
        2905799,
        2918598,
        2937506,
        2950419,
        2962145,
        2977872,
        2989060,
        3013455,
        3037935,
        3067025,
        3085865,
        3101072,
        3125371,
        3133464,
        3135071,
        3145542,
        3155590,
        3157950,
        3162985,
        3169833,
        3167131,
        3159101,
        3158136,
        3172336,
        3176992,
        3182541,
        3197971,
        3212302,
        3220407,
        3233209,
        3256397,
        3269129,
        3280691,
        3312463,
        3319911,
        3329074,
        3337370,
        3358564,
        3368180,
        3382265,
        3397399,
        3412208,
        3430659,
        3436406,
        3455104,
        3485231,
        3482856,
        3493517,
        3496684,
        3498629,
        3514659,
        3533982,
        3548645,
        3558109,
        3570962,
        3595263,
        3600773,
        3615677,
        3638426,
        3656642,
        3666674,
        3695000,
        3718207,
        3742800,
        3735036,
        3747240,
        3756213,
        3776275,
        3805327,
        3848054,
        3930982,
        3905442,
        3930847,
        3952443,
        3968746,
        3988595,
        4023726,
        4024225,
        4029253,
        4052935,
        4066747,
        4078868,
        4121606,
        4136412,
        4149339,
        4174322,
        4168507,
        4171277,
        4183450,
        4209465,
        4212330,
        4225858,
        4226830,
        4226952,
        4340387,
        4363192,
        4382791,
        4412550,
        4429759,
        4467986,
        4481145,
        4501923,
        4533918,
        4553696,
        4588671,
        4615510,
        4645232,
        4650397,
        4662027,
        4697507,
        4719009,
        4735880,
        4761547,
        4785365,
        4821013,
        4847022,
        4890882,
        4915147,
        4922129,
        4968610,
        5000011,
        5048210,
        5088934,
        5096544,
        5123636,
        5160933,
        5167505,
        5200531,
        5217471,
        5238327,
        5259980,
        5281581,
        5316424,
        5341144,
        5355734,
        5385279,
        5421035,
        5438154,
        5484081,
        5518152,
        5542737,
        5573540,
        5623288,
        5653315,
        5679341,
        5721454,
        5762299,
        5824959,
        5885266,
        5914509,
        5980748,
        6001860,
        6027064,
        6093186,
        6124570,
        6175649,
        6222149,
        6295495,
        6317503,
        6363553,
        6369246,
        6406721,
        6486139,
        6500180,
        6556170,
        6663329,
        6705357,
        6739280,
        6825507,
        6850746,
        6917829,
        6987296,
        7057569,
        7100108,
        7161755,
        7267682,
        7323179,
        7356073,
        7440745,
        7505318,
        7536659,
        7616022,
        7674618,
        7700435,
        7750811,
        7787840,
        7865188,
        8010727,
        8035211,
        8041762,
        8089401,
        8112143,
        8093515,
        8145669,
        8140833,
        8155197,
        8184207,
        8176976,
        8189516,
        8195862,
        8181093,
        8207839,
        8220765,
        8228832,
        8230444,
        8264563,
        8283333,
        8314433,
        8331067,
        8367919,
        8367910,
        8387527,
        8404159,
        8423299,
        8436054,
        8444617,
        8458122,
        8456009,
        8480338,
        8495988,
        8509521,
        8558299,
        8593759,
        8572193,
        8588089,
        8607320,
        8644031,
        8679871,
        8723292,
        8704188,
        8746773,
        8779098,
        8829323,
        8846566,
        8875881,
        8948155,
        8975122,
        8998474,
        9014275,
        9049240,
        9079682,
        9108326,
        9129445,
        9126627,
        9147571,
        9183775,
        9198843,
        9219721,
        9235023,
        9212026,
        9239268,
        9267544,
        9284719,
        9287884,
        9337820,
        9362807,
        9390708,
        9433034,
        9482753,
        9500212,
        9559214,
        9676028,
        9745960,
        9761926,
        9815782,
        9865617,
        9909778,
        9947884,
        10012113,
        10030998,
        10060424,
        10124558,
        10182417,
        10217313,
        10268839,
        10320213,
        10342705,
        10383940,
        10423954,
        10452292,
        10502607,
        10528589,
        10569166,
        10591645,
        10662425,
        10710530,
        10759056,
        10814115,
        10881654,
        10912228,
        10928508,
        10988182,
        11008582,
        11066852,
        11095402,
        11139576,
        11176686,
        11208278,
        11269445,
        11279345,
        11291178,
        11338310,
        11421681,
        11493439,
        11495367,
        11513477,
        11560774,
        11622671,
        11667007,
        11711034,
        11749319,
        11809936,
        11891739,
        11966973,
        12032382,
        12070935,
        12137470,
        12239218,
        12279671,
        12337796,
        12376509,
        12377539,
        12416744,
        12487012,
        12793133,
        12975064,
        13130131,
        13220879,
        13289697,
        13347514,
        13448249,
        13541984,
        13636887,
        13742922,
        13827290,
        13914884,
        14019911,
        14066290,
        14155412,
        14232234,
        14331372,
        14422526,
        14492634,
        14566489,
        14613302,
        14712119,
        14830219,
        14912392,
        14976033,
        15025587,
        15073693,
        15140759,
        15238354,
        15377648,
        15422178,
        15373322,
        15312129,
        15237981,
        15269069,
        15222184,
        15178734,
        15120271,
        15105451,
        15086706,
        15063603,
        15038755,
        15062795,
        15039414,
        15036237,
        15111993,
        15083328,
        15103809,
        15118968,
        15142798,
        15179106,
        15283438,
        15257981,
        15328063,
        15400882,
        15430200,
        15530867,
        15603787,
        15581930,
        15622800,
        15658278,
        15688806,
        15723358,
        15723085,
        15736526,
        15754917,
        15788711,
        15900932,
        16024599,
        16077214,
        16203430,
        16244574,
        16277495
      ],
      "m3": [
        1097404,
        1105520,
        1117228,
        1122639,
        1130672,
        1139157,
        1150687,
        1157482,
        1164470,
        1176441,
        1192713,
        1198927,
        1209209,
        1222048,
        1233640,
        1244293,
        1257592,
        1266536,
        1275262,
        1280121,
        1293408,
        1302173,
        1313067,
        1324037,
        1338805,
        1350759,
        1366026,
        1376835,
        1385084,
        1403542,
        1414886,
        1429591,
        1440564,
        1448567,
        1461236,
        1478452,
        1488249,
        1498226,
        1505297,
        1516179,
        1527129,
        1538465,
        1550957,
        1563091,
        1569280,
        1581495,
        1595252,
        1607971,
        1616845,
        1623473,
        1633342,
        1643658,
        1659252,
        1668177,
        1681799,
        1697027,
        1711302,
        1717983,
        1729206,
        1742791,
        1758943,
        1776558,
        1788333,
        1797511,
        1804082,
        1812216,
        1823517,
        1831278,
        1840516,
        1849577,
        1856300,
        1882118,
        1891332,
        1899853,
        1919041,
        1917327,
        1927726,
        1936535,
        1950177,
        1961502,
        1976548,
        1995452,
        2004194,
        2011545,
        2026350,
        2038106,
        2053663,
        2069485,
        2084022,
        2095216,
        2109659,
        2123852,
        2137689,
        2155101,
        2168100,
        2173838,
        2186450,
        2197901,
        2210937,
        2234863,
        2252687,
        2262415,
        2280986,
        2300792,
        2315101,
        2334535,
        2349769,
        2358041,
        2374823,
        2393302,
        2423922,
        2431297,
        2452172,
        2480570,
        2502846,
        2519586,
        2534023,
        2548639,
        2568371,
        2593728,
        2621156,
        2636316,
        2644762,
        2655640,
        2670162,
        2786501,
        2804287,
        2823790,
        2846434,
        2864450,
        2884653,
        2907362,
        2923138,
        2947536,
        2954443,
        2969291,
        2986959,
        3003602,
        3025478,
        3050014,
        3064203,
        3083316,
        3109460,
        3132988,
        3137429,
        3152683,
        3174957,
        3206393,
        3232729,
        3249564,
        3271402,
        3285469,
        3332285,
        3336785,
        3361978,
        3365086,
        3378259,
        3396757,
        3441196,
        3450523,
        3469532,
        3479485,
        3487064,
        3503529,
        3515151,
        3540903,
        3562936,
        3588556,
        3598429,
        3606066,
        3622879,
        3633025,
        3632446,
        3642375,
        3656552,
        3656590,
        3656168,
        3670601,
        3678013,
        3672401,
        3679631,
        3700799,
        3698901,
        3709760,
        3730389,
        3752177,
        3758401,
        3781841,
        3804491,
        3820462,
        3840964,
        3877110,
        3891983,
        3906146,
        3919392,
        3933563,
        3940474,
        3948661,
        3963579,
        3982902,
        4002704,
        4007200,
        4016115,
        4037575,
        4040762,
        4054012,
        4061573,
        4068933,
        4097362,
        4121578,
        4143617,
        4146012,
        4169047,
        4191990,
        4201492,
        4222019,
        4244379,
        4255439,
        4267921,
        4298513,
        4316033,
        4340943,
        4362649,
        4368163,
        4371401,
        4410036,
        4417203,
        4422982,
        4447197,
        4436979,
        4453500,
        4488386,
        4505279,
        4537054,
        4565970,
        4572050,
        4594744,
        4616547,
        4646110,
        4667221,
        4713205,
        4735956,
        4766006,
        4802801,
        4795425,
        4788838,
        4803137,
        4828781,
        4830524,
        4847849,
        4851550,
        4859203,
        5024537,
        5049678,
        5079966,
        5111811,
        5142003,
        5192173,
        5214090,
        5249306,
        5296229,
        5334043,
        5371237,
        5402883,
        5424797,
        5431456,
        5453968,
        5482865,
        5523451,
        5539079,
        5568190,
        5606774,
        5660669,
        5680917,
        5733178,
        5767431,
        5809186,
        5857436,
        5880069,
        5957074,
        5983094,
        5990357,
        6028830,
        6054734,
        6057142,
        6110399,
        6134302,
        6148767,
        6165335,
        6201786,
        6232560,
        6260857,
        6265034,
        6315025,
        6354328,
        6375262,
        6417367,
        6461295,
        6484681,
        6540370,
        6573488,
        6608114,
        6628904,
        6682171,
        6731012,
        6807158,
        6876098,
        6910851,
        6972348,
        6991045,
        7026011,
        7087688,
        7120559,
        7170882,
        7221902,
        7303181,
        7347101,
        7384631,
        7403368,
        7475572,
        7573385,
        7598494,
        7652322,
        7753569,
        7838901,
        7889608,
        8008864,
        8032194,
        8131881,
        8206302,
        8290084,
        8344331,
        8418602,
        8541400,
        8631497,
        8647959,
        8793038,
        8843329,
        8867136,
        8940964,
        9020742,
        9044137,
        9107460,
        9143592,
        9224888,
        9369285,
        9387004,
        9402372,
        9402776,
        9436867,
        9403303,
        9451115,
        9421585,
        9428787,
        9433131,
        9387590,
        9414236,
        9383509,
        9354834,
        9349315,
        9324051,
        9323604,
        9332304,
        9377955,
        9388633,
        9240895,
        9234411,
        9264711,
        9272702,
        9268660,
        9287184,
        9298808,
        9318798,
        9327053,
        9345311,
        9350480,
        9369117,
        9386874,
        9390737,
        9461608,
        9494473,
        9454437,
        9471859,
        9498551,
        9508245,
        9535017,
        9610720,
        9575598,
        9627462,
        9658453,
        9705253,
        9697121,
        9713753,
        9774469,
        9777752,
        9785187,
        9767605,
        9784933,
        9803199,
        9822063,
        9837477,
        9818212,
        9832329,
        9874715,
        9868977,
        9877942,
        9885297,
        9832650,
        9874481,
        9896754,
        9891849,
        9879815,
        9941588,
        9973532,
        10007330,
        10049824,
        10098645,
        10125070,
        10184921,
        10326597,
        10405448,
        10438257,
        10475465,
        10545103,
        10561797,
        10582758,
        10656208,
        10662405,
        10694197,
        10780760,
        10836416,
        10842557,
        10909372,
        10976218,
        10986982,
        11039392,
        11084382,
        11119739,
        11178145,
        11199036,
        11240372,
        11263126,
        11337510,
        11382913,
        11439966,
        11491550,
        11581144,
        11578021,
        11607575,
        11652740,
        11668038,
        11736671,
        11773187,
        11804155,
        11849209,
        11858924,
        11912335,
        11920924,
        11947415,
        11997019,
        12069661,
        12148975,
        12133685,
        12159090,
        12192728,
        12261531,
        12302563,
        12367971,
        12401824,
        12455375,
        12535013,
        12606426,
        12676642,
        12713460,
        12783156,
        12887912,
        12921691,
        12974640,
        13005644,
        12981800,
        13055432,
        13141315,
        13488513,
        13642154,
        13798960,
        13908323,
        13990615,
        14034136,
        14152539,
        14252307,
        14349658,
        14477108,
        14581808,
        14662099,
        14761227,
        14812305,
        14908189,
        14987867,
        15105721,
        15197325,
        15253663,
        15361111,
        15414738,
        15499049,
        15602419,
        15663642,
        15729145,
        15798329,
        15850911,
        15929996,
        15989616,
        16139776,
        16195744,
        16147078,
        16130632,
        16059190,
        16077692,
        16064150,
        16040580,
        15980064,
        16000316,
        15980596,
        15960510,
        15950092,
        15986569,
        15985134,
        15995129,
        16108579,
        16096551,
        16113985,
        16174841,
        16210219,
        16240717,
        16361315,
        16366929,
        16464268,
        16540224,
        16582010,
        16682669,
        16776476,
        16768099,
        16826210,
        16838607,
        16883244,
        16915764,
        16927287,
        16922174,
        16926414,
        16982252,
        17073963,
        17200583,
        17204147,
        17340023,
        17367374,
        17446547
      ]
    },
    "keyRates": {
      "times": [
        "1999-01-01",
        "1999-01-04",
        "1999-01-22",
        "1999-04-09",
        "1999-11-05",
        "2000-02-04",
        "2000-03-17",
        "2000-04-28",
        "2000-06-09",
        "2000-06-28",
        "2000-09-01",
        "2000-10-06",
        "2001-05-11",
        "2001-08-31",
        "2001-09-18",
        "2001-11-09",
        "2002-12-06",
        "2003-03-07",
        "2003-06-06",
        "2005-12-06",
        "2006-03-08",
        "2006-06-15",
        "2006-08-09",
        "2006-10-11",
        "2006-12-13",
        "2007-03-14",
        "2007-06-13",
        "2008-07-09",
        "2008-10-08",
        "2008-10-09",
        "2008-10-15",
        "2008-11-12",
        "2008-12-10",
        "2009-01-21",
        "2009-03-11",
        "2009-04-08",
        "2009-05-13",
        "2011-04-13",
        "2011-07-13",
        "2011-11-09",
        "2011-12-14",
        "2012-07-11",
        "2013-05-08",
        "2013-11-13",
        "2014-06-11",
        "2014-09-10",
        "2015-12-09",
        "2016-03-16",
        "2019-09-18",
        "2022-07-27",
        "2022-09-14",
        "2022-11-02",
        "2022-12-21",
        "2023-02-08",
        "2023-03-22",
        "2023-05-10",
        "2023-06-21",
        "2023-08-02",
        "2023-09-20",
        "2024-06-12",
        "2024-09-18",
        "2024-10-23",
        "2024-12-18",
        "2025-02-05",
        "2025-03-12",
        "2025-04-23",
        "2025-06-11"
      ],
      "series": {
        "MRR": [
          3,
          3,
          3,
          2.5,
          3,
          3.25,
          3.5,
          3.75,
          4.25,
          4.25,
          4.25,
          4.25,
          4.25,
          4.25,
          4.25,
          4.25,
          4.25,
          4.25,
          4.25,
          4.25,
          4.25,
          4.25,
          4.25,
          4.25,
          4.25,
          4.25,
          4.25,
          4.25,
          4.25,
          4.25,
          3.75,
          3.25,
          2.5,
          2,
          1.5,
          1.25,
          1,
          1.25,
          1.5,
          1.25,
          1,
          0.75,
          0.5,
          0.25,
          0.15,
          0.05,
          0.05,
          0,
          0,
          0.5,
          1.25,
          2,
          2.5,
          3,
          3.5,
          3.75,
          4,
          4.25,
          4.5,
          4.25,
          3.65,
          3.4,
          3.15,
          2.9,
          2.65,
          2.4,
          2.15
        ],
        "DFR": [
          2,
          2.75,
          2,
          1.5,
          2,
          2.25,
          2.5,
          2.75,
          3.25,
          3.25,
          3.5,
          3.75,
          3.5,
          3.25,
          2.75,
          2.25,
          1.75,
          1.5,
          1,
          1.25,
          1.5,
          1.75,
          2,
          2.25,
          2.5,
          2.75,
          3,
          3.25,
          2.75,
          3.25,
          3.25,
          2.75,
          2,
          1,
          0.5,
          0.25,
          0.25,
          0.5,
          0.75,
          0.5,
          0.25,
          0,
          0,
          0,
          -0.1,
          -0.2,
          -0.3,
          -0.4,
          -0.5,
          0,
          0.75,
          1.5,
          2,
          2.5,
          3,
          3.25,
          3.5,
          3.75,
          4,
          3.75,
          3.5,
          3.25,
          3,
          2.75,
          2.5,
          2.25,
          2
        ],
        "MLFR": [
          4.5,
          3.25,
          4.5,
          3.5,
          4,
          4.25,
          4.5,
          4.75,
          5.25,
          5.25,
          5.5,
          5.75,
          5.5,
          5.25,
          4.75,
          4.25,
          3.75,
          3.5,
          3,
          3.25,
          3.5,
          3.75,
          4,
          4.25,
          4.5,
          4.75,
          5,
          5.25,
          4.75,
          4.25,
          4.25,
          3.75,
          3,
          3,
          2.5,
          2.25,
          1.75,
          2,
          2.25,
          2,
          1.75,
          1.5,
          1,
          0.75,
          0.4,
          0.3,
          0.3,
          0.25,
          0.25,
          0.75,
          1.5,
          2.25,
          2.75,
          3.25,
          3.75,
          4,
          4.25,
          4.5,
          4.75,
          4.5,
          3.9,
          3.65,
          3.4,
          3.15,
          2.9,
          2.65,
          2.4
        ]
      },
      "labels": {
        "MRR": "MRO (refinancovacia)",
        "DFR": "Depozitná",
        "MLFR": "Marginálna"
      }
    },
    "euribor": {
      "times": [
        "1994-01",
        "1994-02",
        "1994-03",
        "1994-04",
        "1994-05",
        "1994-06",
        "1994-07",
        "1994-08",
        "1994-09",
        "1994-10",
        "1994-11",
        "1994-12",
        "1995-01",
        "1995-02",
        "1995-03",
        "1995-04",
        "1995-05",
        "1995-06",
        "1995-07",
        "1995-08",
        "1995-09",
        "1995-10",
        "1995-11",
        "1995-12",
        "1996-01",
        "1996-02",
        "1996-03",
        "1996-04",
        "1996-05",
        "1996-06",
        "1996-07",
        "1996-08",
        "1996-09",
        "1996-10",
        "1996-11",
        "1996-12",
        "1997-01",
        "1997-02",
        "1997-03",
        "1997-04",
        "1997-05",
        "1997-06",
        "1997-07",
        "1997-08",
        "1997-09",
        "1997-10",
        "1997-11",
        "1997-12",
        "1998-01",
        "1998-02",
        "1998-03",
        "1998-04",
        "1998-05",
        "1998-06",
        "1998-07",
        "1998-08",
        "1998-09",
        "1998-10",
        "1998-11",
        "1998-12",
        "1999-01",
        "1999-02",
        "1999-03",
        "1999-04",
        "1999-05",
        "1999-06",
        "1999-07",
        "1999-08",
        "1999-09",
        "1999-10",
        "1999-11",
        "1999-12",
        "2000-01",
        "2000-02",
        "2000-03",
        "2000-04",
        "2000-05",
        "2000-06",
        "2000-07",
        "2000-08",
        "2000-09",
        "2000-10",
        "2000-11",
        "2000-12",
        "2001-01",
        "2001-02",
        "2001-03",
        "2001-04",
        "2001-05",
        "2001-06",
        "2001-07",
        "2001-08",
        "2001-09",
        "2001-10",
        "2001-11",
        "2001-12",
        "2002-01",
        "2002-02",
        "2002-03",
        "2002-04",
        "2002-05",
        "2002-06",
        "2002-07",
        "2002-08",
        "2002-09",
        "2002-10",
        "2002-11",
        "2002-12",
        "2003-01",
        "2003-02",
        "2003-03",
        "2003-04",
        "2003-05",
        "2003-06",
        "2003-07",
        "2003-08",
        "2003-09",
        "2003-10",
        "2003-11",
        "2003-12",
        "2004-01",
        "2004-02",
        "2004-03",
        "2004-04",
        "2004-05",
        "2004-06",
        "2004-07",
        "2004-08",
        "2004-09",
        "2004-10",
        "2004-11",
        "2004-12",
        "2005-01",
        "2005-02",
        "2005-03",
        "2005-04",
        "2005-05",
        "2005-06",
        "2005-07",
        "2005-08",
        "2005-09",
        "2005-10",
        "2005-11",
        "2005-12",
        "2006-01",
        "2006-02",
        "2006-03",
        "2006-04",
        "2006-05",
        "2006-06",
        "2006-07",
        "2006-08",
        "2006-09",
        "2006-10",
        "2006-11",
        "2006-12",
        "2007-01",
        "2007-02",
        "2007-03",
        "2007-04",
        "2007-05",
        "2007-06",
        "2007-07",
        "2007-08",
        "2007-09",
        "2007-10",
        "2007-11",
        "2007-12",
        "2008-01",
        "2008-02",
        "2008-03",
        "2008-04",
        "2008-05",
        "2008-06",
        "2008-07",
        "2008-08",
        "2008-09",
        "2008-10",
        "2008-11",
        "2008-12",
        "2009-01",
        "2009-02",
        "2009-03",
        "2009-04",
        "2009-05",
        "2009-06",
        "2009-07",
        "2009-08",
        "2009-09",
        "2009-10",
        "2009-11",
        "2009-12",
        "2010-01",
        "2010-02",
        "2010-03",
        "2010-04",
        "2010-05",
        "2010-06",
        "2010-07",
        "2010-08",
        "2010-09",
        "2010-10",
        "2010-11",
        "2010-12",
        "2011-01",
        "2011-02",
        "2011-03",
        "2011-04",
        "2011-05",
        "2011-06",
        "2011-07",
        "2011-08",
        "2011-09",
        "2011-10",
        "2011-11",
        "2011-12",
        "2012-01",
        "2012-02",
        "2012-03",
        "2012-04",
        "2012-05",
        "2012-06",
        "2012-07",
        "2012-08",
        "2012-09",
        "2012-10",
        "2012-11",
        "2012-12",
        "2013-01",
        "2013-02",
        "2013-03",
        "2013-04",
        "2013-05",
        "2013-06",
        "2013-07",
        "2013-08",
        "2013-09",
        "2013-10",
        "2013-11",
        "2013-12",
        "2014-01",
        "2014-02",
        "2014-03",
        "2014-04",
        "2014-05",
        "2014-06",
        "2014-07",
        "2014-08",
        "2014-09",
        "2014-10",
        "2014-11",
        "2014-12",
        "2015-01",
        "2015-02",
        "2015-03",
        "2015-04",
        "2015-05",
        "2015-06",
        "2015-07",
        "2015-08",
        "2015-09",
        "2015-10",
        "2015-11",
        "2015-12",
        "2016-01",
        "2016-02",
        "2016-03",
        "2016-04",
        "2016-05",
        "2016-06",
        "2016-07",
        "2016-08",
        "2016-09",
        "2016-10",
        "2016-11",
        "2016-12",
        "2017-01",
        "2017-02",
        "2017-03",
        "2017-04",
        "2017-05",
        "2017-06",
        "2017-07",
        "2017-08",
        "2017-09",
        "2017-10",
        "2017-11",
        "2017-12",
        "2018-01",
        "2018-02",
        "2018-03",
        "2018-04",
        "2018-05",
        "2018-06",
        "2018-07",
        "2018-08",
        "2018-09",
        "2018-10",
        "2018-11",
        "2018-12",
        "2019-01",
        "2019-02",
        "2019-03",
        "2019-04",
        "2019-05",
        "2019-06",
        "2019-07",
        "2019-08",
        "2019-09",
        "2019-10",
        "2019-11",
        "2019-12",
        "2020-01",
        "2020-02",
        "2020-03",
        "2020-04",
        "2020-05",
        "2020-06",
        "2020-07",
        "2020-08",
        "2020-09",
        "2020-10",
        "2020-11",
        "2020-12",
        "2021-01",
        "2021-02",
        "2021-03",
        "2021-04",
        "2021-05",
        "2021-06",
        "2021-07",
        "2021-08",
        "2021-09",
        "2021-10",
        "2021-11",
        "2021-12",
        "2022-01",
        "2022-02",
        "2022-03",
        "2022-04",
        "2022-05",
        "2022-06",
        "2022-07",
        "2022-08",
        "2022-09",
        "2022-10",
        "2022-11",
        "2022-12",
        "2023-01",
        "2023-02",
        "2023-03",
        "2023-04",
        "2023-05",
        "2023-06",
        "2023-07",
        "2023-08",
        "2023-09",
        "2023-10",
        "2023-11",
        "2023-12",
        "2024-01",
        "2024-02",
        "2024-03",
        "2024-04",
        "2024-05",
        "2024-06",
        "2024-07",
        "2024-08",
        "2024-09",
        "2024-10",
        "2024-11",
        "2024-12",
        "2025-01",
        "2025-02",
        "2025-03",
        "2025-04",
        "2025-05",
        "2025-06",
        "2025-07",
        "2025-08",
        "2025-09",
        "2025-10",
        "2025-11",
        "2025-12",
        "2026-01",
        "2026-02",
        "2026-03",
        "2026-04"
      ],
      "values": [
        6.91,
        6.86,
        6.75,
        6.57,
        6.24,
        6.3,
        6.34,
        6.43,
        6.38,
        6.43,
        6.4,
        6.69,
        6.66,
        6.59,
        7.58,
        7.29,
        7.04,
        7.08,
        6.92,
        6.66,
        6.5,
        6.75,
        6.45,
        6.32,
        5.81,
        5.58,
        5.5,
        5.27,
        5.06,
        5.08,
        5.06,
        5.08,
        4.86,
        4.69,
        4.57,
        4.5,
        4.39,
        4.43,
        4.5,
        4.39,
        4.3,
        4.29,
        4.3,
        4.36,
        4.31,
        4.44,
        4.49,
        4.37,
        4.26,
        4.24,
        4.11,
        4.09,
        4.06,
        4.02,
        3.95,
        3.93,
        3.93,
        3.81,
        3.69,
        3.37,
        3.1321,
        3.0934,
        3.0466957,
        2.6964545,
        2.5789524,
        2.6266818,
        2.6764545,
        2.6950455,
        2.7266818,
        3.3756667,
        3.4676818,
        3.4460455,
        3.3431429,
        3.5367619,
        3.7470435,
        3.9252778,
        4.3620455,
        4.5017273,
        4.5829048,
        4.777087,
        4.8528095,
        5.0412727,
        5.0919545,
        4.9391579,
        4.7707273,
        4.7558,
        4.7086364,
        4.682,
        4.6366818,
        4.4535714,
        4.4671364,
        4.3535217,
        3.98285,
        3.5998696,
        3.3856818,
        3.3448889,
        3.3387727,
        3.3571,
        3.3908,
        3.4069048,
        3.4671364,
        3.464,
        3.41,
        3.3519091,
        3.3101429,
        3.2612609,
        3.1241429,
        2.94105,
        2.8318182,
        2.68745,
        2.5299524,
        2.53335,
        2.4005238,
        2.1518571,
        2.1300435,
        2.1404286,
        2.1473182,
        2.1435652,
        2.15905,
        2.1463333,
        2.0894762,
        2.07055,
        2.0288261,
        2.04875,
        2.0858571,
        2.1126818,
        2.1160455,
        2.1142727,
        2.1185909,
        2.1473333,
        2.1703182,
        2.1731739,
        2.1454286,
        2.13835,
        2.1371905,
        2.1372381,
        2.1256364,
        2.1110455,
        2.1194286,
        2.1324783,
        2.1391364,
        2.196619,
        2.3608636,
        2.4728571,
        2.5116818,
        2.60035,
        2.7226087,
        2.7937778,
        2.889,
        2.9856818,
        3.1021905,
        3.2264783,
        3.335381,
        3.502,
        3.5971818,
        3.6842105,
        3.7518636,
        3.8182,
        3.8909091,
        3.9752632,
        4.0713636,
        4.1477619,
        4.2161818,
        4.5436087,
        4.7417,
        4.6873913,
        4.6385455,
        4.8483684,
        4.4815455,
        4.3620952,
        4.5963684,
        4.7835,
        4.857381,
        4.9405238,
        4.961,
        4.9651905,
        5.0191818,
        5.113087,
        4.2383,
        3.292619,
        2.4565238,
        1.94305,
        1.6354545,
        1.4223,
        1.2817,
        1.2279091,
        0.9749565,
        0.8604762,
        0.7720909,
        0.7375,
        0.7161905,
        0.7120455,
        0.67975,
        0.6617,
        0.6449565,
        0.6447,
        0.6865238,
        0.7275909,
        0.8488182,
        0.8955,
        0.8805,
        0.9976667,
        1.0420455,
        1.0216957,
        1.0172381,
        1.08675,
        1.1755217,
        1.3212105,
        1.4250909,
        1.4885909,
        1.597619,
        1.552087,
        1.5364545,
        1.5758571,
        1.4846818,
        1.4260952,
        1.2222273,
        1.0482857,
        0.8584545,
        0.7443158,
        0.6849091,
        0.6588571,
        0.4970455,
        0.3323913,
        0.2463,
        0.207913,
        0.192,
        0.1854737,
        0.2049091,
        0.22335,
        0.20605,
        0.2089048,
        0.2012273,
        0.21025,
        0.2214348,
        0.2258636,
        0.2232381,
        0.2258261,
        0.223381,
        0.2735,
        0.2920455,
        0.2881,
        0.3053333,
        0.32975,
        0.3245714,
        0.2414286,
        0.2050435,
        0.1915714,
        0.0970909,
        0.0826087,
        0.0809,
        0.0809048,
        0.0626667,
        0.0482,
        0.0271818,
        0.0047,
        -0.0103684,
        -0.0139091,
        -0.0187391,
        -0.0276667,
        -0.0370455,
        -0.0535909,
        -0.087619,
        -0.1263182,
        -0.14615,
        -0.1835714,
        -0.2285238,
        -0.2491905,
        -0.2571818,
        -0.2679091,
        -0.2945238,
        -0.2982174,
        -0.3016364,
        -0.309,
        -0.3126818,
        -0.3157619,
        -0.3255455,
        -0.3286,
        -0.3293478,
        -0.3303889,
        -0.3294545,
        -0.33,
        -0.3304286,
        -0.329087,
        -0.329381,
        -0.3295455,
        -0.329,
        -0.3278947,
        -0.3284545,
        -0.3285,
        -0.3279048,
        -0.32845,
        -0.3252273,
        -0.3220476,
        -0.3207273,
        -0.319,
        -0.31885,
        -0.3176957,
        -0.3163636,
        -0.3118947,
        -0.308,
        -0.30845,
        -0.3091905,
        -0.31045,
        -0.3118636,
        -0.3289,
        -0.3648696,
        -0.4076818,
        -0.4175714,
        -0.4128696,
        -0.4012857,
        -0.3947,
        -0.3911364,
        -0.40885,
        -0.4166364,
        -0.25405,
        -0.27195,
        -0.376,
        -0.4441304,
        -0.4797143,
        -0.4913636,
        -0.5091364,
        -0.5208571,
        -0.5380909,
        -0.54715,
        -0.5411,
        -0.539087,
        -0.53815,
        -0.5400952,
        -0.5429091,
        -0.5448182,
        -0.5475909,
        -0.5450455,
        -0.5498095,
        -0.5673636,
        -0.5819565,
        -0.5601429,
        -0.5315,
        -0.4954348,
        -0.4478947,
        -0.3857273,
        -0.2392273,
        0.036619,
        0.3947391,
        1.0108636,
        1.4276667,
        1.8252273,
        2.0634762,
        2.3448636,
        2.64035,
        2.9105652,
        3.1794444,
        3.3717273,
        3.5358636,
        3.6718095,
        3.7803043,
        3.8800476,
        3.9676364,
        3.9716364,
        3.9348947,
        3.9252727,
        3.9231905,
        3.9231,
        3.8853333,
        3.8126818,
        3.7245,
        3.6848261,
        3.5475909,
        3.4337143,
        3.1666087,
        3.0067619,
        2.8246,
        2.7042727,
        2.52495,
        2.4424286,
        2.2494,
        2.0872381,
        1.983619,
        1.9863478,
        2.0210952,
        2.0272727,
        2.0344348,
        2.04165,
        2.0484286,
        2.0277273,
        2.0113,
        2.1094091,
        2.1753
      ]
    },
    "yields": {
      "years": [
        1949,
        1950,
        1951,
        1952,
        1953,
        1954,
        1955,
        1956,
        1957,
        1958,
        1959,
        1960,
        1961,
        1962,
        1963,
        1964,
        1965,
        1966,
        1967,
        1968,
        1969,
        1970,
        1971,
        1972,
        1973,
        1974,
        1975,
        1976,
        1977,
        1978,
        1979,
        1980,
        1981,
        1982,
        1983,
        1984,
        1985,
        1986,
        1987,
        1988,
        1989,
        1990,
        1991,
        1992,
        1993,
        1994,
        1995,
        1996,
        1997,
        1998,
        1999,
        2000,
        2001,
        2002,
        2003,
        2004,
        2005,
        2006,
        2007,
        2008,
        2009,
        2010,
        2011,
        2012,
        2013,
        2014,
        2015,
        2016,
        2017,
        2018,
        2019,
        2020,
        2021,
        2022,
        2023,
        2024,
        2025
      ],
      "values": [
        null,
        null,
        null,
        null,
        null,
        null,
        null,
        null,
        null,
        null,
        null,
        null,
        null,
        null,
        null,
        null,
        null,
        null,
        null,
        null,
        null,
        null,
        null,
        null,
        null,
        null,
        null,
        null,
        null,
        null,
        null,
        null,
        null,
        null,
        null,
        null,
        null,
        null,
        null,
        null,
        null,
        null,
        null,
        null,
        null,
        null,
        null,
        null,
        null,
        null,
        null,
        null,
        8.04,
        6.93,
        4.99,
        5.03,
        3.52,
        4.41,
        4.49,
        4.72,
        4.71,
        3.87,
        4.45,
        4.55,
        3.19,
        2.07,
        0.89,
        0.54,
        0.92,
        0.89,
        0.25,
        -0.04,
        -0.08,
        2.07,
        3.65,
        3.47,
        3.42929
      ]
    },
    "inflation": {
      "years": [
        1996,
        1997,
        1998,
        1999,
        2000,
        2001,
        2002,
        2003,
        2004,
        2005,
        2006,
        2007,
        2008,
        2009,
        2010,
        2011,
        2012,
        2013,
        2014,
        2015,
        2016,
        2017,
        2018,
        2019,
        2020,
        2021,
        2022,
        2023,
        2024,
        2025
      ],
      "values": [
        5.8,
        6,
        6.7,
        10.4,
        12.2,
        7.2,
        3.5,
        8.4,
        7.5,
        2.8,
        4.3,
        1.9,
        3.9,
        0.9,
        0.7,
        4.1,
        3.7,
        1.5,
        -0.1,
        -0.3,
        -0.5,
        1.4,
        2.5,
        2.8,
        2,
        2.8,
        12.1,
        11,
        3.2,
        4.2
      ]
    },
    "velocity": {
      "years": [
        1975,
        1976,
        1977,
        1978,
        1979,
        1980,
        1981,
        1982,
        1983,
        1984,
        1985,
        1986,
        1987,
        1988,
        1989,
        1990,
        1991,
        1992,
        1993,
        1994,
        1995,
        1996,
        1997,
        1998,
        1999,
        2000,
        2001,
        2002,
        2003,
        2004,
        2005,
        2006,
        2007,
        2008,
        2009,
        2010,
        2011,
        2012,
        2013,
        2014,
        2015,
        2016,
        2017,
        2018,
        2019,
        2020,
        2021,
        2022,
        2023,
        2024,
        2025
      ],
      "velocity": [
        null,
        null,
        null,
        null,
        null,
        null,
        null,
        null,
        null,
        null,
        null,
        null,
        null,
        null,
        null,
        null,
        null,
        null,
        null,
        null,
        1.7877905722024088,
        1.7704456859071165,
        1.7371935421130151,
        1.7159225268563356,
        1.6777146631806283,
        1.6875734996698026,
        1.6532687275085594,
        1.6065172291316026,
        1.5434032531660584,
        1.5183364647015911,
        1.4570494522027209,
        1.4091804646568107,
        1.3496739829902302,
        1.2546573144209365,
        1.150236873575126,
        1.1594445762483105,
        1.1648669359698316,
        1.1292117294574127,
        1.1000925084659658,
        1.0953537630797525,
        1.0690684226926026,
        1.0451060639572833,
        1.0336403291190328,
        1.0239786009572542,
        1.0028493402747405,
        0.8820441503414765,
        0.8836904236337282,
        0.9075384557836167,
        0.9703656717262393,
        0.996376087944861,
        1.0030952959733614
      ],
      "gdp": [
        null,
        null,
        null,
        null,
        null,
        null,
        null,
        null,
        null,
        null,
        null,
        null,
        null,
        null,
        null,
        null,
        null,
        null,
        null,
        null,
        5761538.6,
        6006586.8,
        6153972.8,
        6404093.7,
        6704260.9,
        7060575.2,
        7394454.9,
        7648498.4,
        7875580.5,
        8213927.1,
        8519767.5,
        8981259.5,
        9480602.8,
        9719969.9,
        9381356,
        9645057.2,
        9920813.4,
        9951251.2,
        10057096.5,
        10298332.7,
        10661709.8,
        10952442,
        11368245,
        11747059.3,
        12140284.1,
        11615802.3,
        12618691.5,
        13758305.3,
        14663455.4,
        15233197.7,
        15822253.1
      ],
      "m2Avg": [
        null,
        null,
        null,
        null,
        null,
        1116008.1666666667,
        1225134.1666666667,
        1352441.9166666667,
        1480218.4166666667,
        1599976.75,
        1727679.75,
        1846051.5833333333,
        1977191.0833333333,
        2107755.75,
        2266074.8333333335,
        2467594.6666666665,
        2647498.5833333335,
        2792600.0833333335,
        2958216.8333333335,
        3141581.25,
        3222714.5,
        3392697.5833333335,
        3542479.6666666665,
        3732157.8333333335,
        3996067.4166666665,
        4183862.3333333335,
        4472627.333333333,
        4760919,
        5102736.75,
        5409820.083333333,
        5847274.083333333,
        6373392,
        7024365.083333333,
        7747111.333333333,
        8156020.916666667,
        8318687.583333333,
        8516692.416666666,
        8812564.5,
        9142046.166666666,
        9401832.583333334,
        9972897.5,
        10479742.083333334,
        10998259.916666666,
        11471977.333333334,
        12105790.583333334,
        13169184.666666666,
        14279538.583333334,
        15160024.583333334,
        15111267.666666666,
        15288602.25,
        15773429.666666666
      ]
    }
  }
}